metaTED/__init__.py
metaTED/cache.py
metaTED/metalink.py
metaTED/crawler/__init__.py
metaTED/crawler/get_downloadable_talks.py
metaTED/crawler/get_supported_subtitle_languages.py
metaTED/crawler/get_talk_info.py
metaTED/crawler/get_talks_urls.py
metaTED/templates/template.metalink
metaTED-2.1.5.dist-info/AUTHORS
metaTED-2.1.5.dist-info/LICENSE
metaTED-2.1.5.dist-info/METADATA
metaTED-2.1.5.dist-info/WHEEL
metaTED-2.1.5.dist-info/entry_points.txt
metaTED-2.1.5.dist-info/top_level.txt
metaTED-2.1.5.dist-info/RECORD
