Metadata-Version: 2.1
Name: metaTED
Version: 2.1.5
Summary: Creates metalink files of TED talks for easier downloading
Home-page: https://gitlab.com/petar.maric/metated
Author: Petar Maric
Author-email: petar.maric@gmail.com
License: BSD
Download-URL: http://pypi.python.org/pypi/metaTED
Keywords: TED metalink download video
Platform: any
Classifier: Development Status :: 5 - Production/Stable
Classifier: Environment :: Console
Classifier: Intended Audience :: End Users/Desktop
Classifier: License :: OSI Approved :: BSD License
Classifier: Operating System :: OS Independent
Classifier: Programming Language :: Python :: 2.6
Classifier: Topic :: Internet :: WWW/HTTP
Classifier: Topic :: Internet :: WWW/HTTP :: Indexing/Search
Classifier: Topic :: Utilities
Requires-Dist: futures (>=2.1)
Requires-Dist: Jinja2 (>=2.1)
Requires-Dist: lxml (>=2.2)
Requires-Dist: shove (<0.3,>=0.2.2)
